setuptools_autover/__init__.py
setuptools_autover/autover.py
setuptools_autover/errors.py
setuptools_autover/git.py
setuptools_autover/pep440.py
setuptools_autover/run.py
setuptools_autover/types.py
setuptools_autover/util.py
setuptools_autover-1.0.2.dist-info/LICENSE.txt
setuptools_autover-1.0.2.dist-info/METADATA
setuptools_autover-1.0.2.dist-info/WHEEL
setuptools_autover-1.0.2.dist-info/entry_points.txt
setuptools_autover-1.0.2.dist-info/top_level.txt
setuptools_autover-1.0.2.dist-info/RECORD
