Metadata-Version: 2.1
Name: setuptools-autover
Version: 1.0.2
Summary: Automatic package version numbering from version control
Home-page: https://github.com/janneronkko/setuptools_autover
Author: Janne Rönkkö
Author-email: janne.ronkko@iki.fi
License: MIT
Keywords: setuptools development git version
Platform: UNKNOWN
Classifier: Development Status :: 5 - Production/Stable
Classifier: Intended Audience :: Developers
Classifier: License :: OSI Approved :: MIT License
Classifier: Operating System :: OS Independent
Classifier: Programming Language :: Python :: 3.5
Classifier: Programming Language :: Python :: 3.6
Classifier: Programming Language :: Python :: 3.7
Classifier: Programming Language :: Python :: 3.8
Classifier: Topic :: System :: Archiving :: Packaging
Requires-Python: >=3.5
